{
    "headers": {
        "content-type": "application/json;charset=UTF-8",
        "user-agent": "Mozilla/5.0 (Windows NT 10.0; Win64; x64) AppleWebKit/537.36 (KHTML, like Gecko) Chrome/91.0.4472.77 Safari/537.36",
        "x-1p-inc-sid": "H1-0eZuWejjSW4Hw0u0Hi7eeux2FaYwrrKBx2Fl-18x2ddx2F1TIuhsDi56ZPQtUZbfUAx3Dx3DBSQO3qE537U881tx2Bghomagx3Dx3D-WwpRYkX4Gz8e7T4uNl5SUQx3Dx3D-wBEj1mx2B0mykql8H4kstFLwx3Dx3D"
    },
    "url1": "https://jcr.clarivate.com/api/jcr3/bwjournal/v1/search-result",
    "payload1": {
        "journalFilterParameters":{
            "query":"","journals":[],"categories":[],"publishers":[],"countryRegions":[],
            "citationIndexes":["SCIE","SSCI","AHCI","ESCI"],"jcrYear":2020,
            "categorySchema":"WOS","openAccess":"N","jifQuartiles":[],"jifRanges":[],"jciRanges":[],"oaRanges":[]
        },
        "retrievalParameters":{
            "start":1,"count":200,"sortBy":"jif2019","sortOrder":"DESC"
        }
    },
    "url2": "https://jcr.clarivate.com/api/jcr3/journalprofile/v1/journal-information",
    "payload2": {
        "journal":"CA-CANCER J CLIN","year":"2020"
    }
}